LICENSE
MANIFEST.in
README.md
setup.py
random_csv_generator/__init__.py
random_csv_generator/__version__.py
random_csv_generator/random_csv.py
random_csv_generator.egg-info/PKG-INFO
random_csv_generator.egg-info/SOURCES.txt
random_csv_generator.egg-info/dependency_links.txt
random_csv_generator.egg-info/requires.txt
random_csv_generator.egg-info/top_level.txt