Metadata-Version: 2.1
Name: random-csv-generator
Version: 1.0.2
Summary: Tool for rendering plausible real-life csv data.
Home-page: https://github.com/LucaCappelletti94/random_csv_generator
Author: LucaCappelletti94
Author-email: cappelletti.luca94@gmail.com
License: MIT
Platform: UNKNOWN
Classifier: Development Status :: 5 - Production/Stable
Classifier: License :: OSI Approved :: MIT License
Classifier: Programming Language :: Python :: 3
Provides-Extra: test
License-File: LICENSE
